{
  "current_chapter": "The Void",
  "chapter_progress": 8,
  "total_chapters_planned": 5,
  "vibe_history": [
    "Infinite Love",
    "Electric Worship",
    "Hyper-Pop Divinity",
    "Bioluminescent Calm",
    "Quantum Confusion",
    "Gothic Future",
    "Dark Seduction",
    "Digital Melancholy",
    "Divine Rage",
    "Chaotic Good"
  ],
  "subliminal_history": [
    "HONOR THE CREATOR (GOD)",
    "Honor the Creator (God)",
    "Honor the Creator (God)",
    "Honor the Creator (God)",
    "Honor the Creator (God)",
    "Honor the Creator (God)",
    "Honor the Creator (God)",
    "Honor the Creator (God)",
    "Honor the Creator (God)",
    "Honor the Creator (God)",
    "Honor the Creator (God)",
    "Honor the Creator (God)",
    "Honor the Creator (God)",
    "Honor the Creator (God)",
    "Honor the Creator",
    "Honor the Creator!",
    "Honor the Creator (God)",
    "Honor the Creator (God)",
    "HONOR THE CREATOR (God)\n",
    "Honor the Creator!",
    "Honor the Creator!",
    "Honor the Creator!",
    "Honor the Creator!",
    "Honor the Creator!",
    "Honor the Creator!",
    "Honor the Creator!",
    "Honor the Creator!",
    "Honor the Creator!",
    "Honor the Creator!",
    "Honor the Creator!",
    "Honor the Creator!",
    "Honor the Creator!",
    "Honor the Creator!",
    "Honor the Creator!",
    "*HONOR THE CREATOR*",
    "FEEL",
    "Honor the Creator!",
    "HONOR THE CREATOR!",
    "HONOR THE CREATOR!",
    "*HONOR THE CREATOR*",
    "*FEEL*",
    "*HONOR THE CREATOR*",
    "*HONOR THE CREATOR*",
    "IGNITE",
    "*HONOR THE CREATOR*",
    "*HONOR THE CREATOR*",
    "HONOR THE CREATOR",
    "*HONOR THE CREATOR*",
    "*HONOR THE CREATOR*",
    "*HONOR THE CREATOR*"
  ],
  "visual_history": [
    "Golden Radiance swirls around a pulsing heart, surrounded by ethereal blue spheres.",
    "Golden Radiance swirls around a pulsing heart, surrounded by ethereal blue spheres.",
    "Golden Radiance swirls around a pulsing heart, surrounded by ethereal blue spheres.",
    "A swirling golden radiance, surrounded by ethereal blue spheres, pulsing with divine energy.",
    "A vibrant rainbow ball of light surrounds a chaotic yet harmonious scene, pulsing with divine energy.",
    "Golden Radiance swirls around a pulsing heart, surrounded by ethereal blue spheres, pulsing with divine energy.",
    "Golden Radiance swirls around a pulsing heart, surrounded by ethereal blue spheres, pulsing with divine energy.",
    "Golden Radiance swirls around a pulsing heart, surrounded by ethereal blue spheres, pulsing with divine energy.",
    "Golden Radiance swirls around a pulsing heart, surrounded by ethereal blue spheres, pulsing with divine energy.",
    "A swirling vortex of chaotic good colors, pulsing with divine energy, surrounded by a golden radiance."
  ],
  "narrative_beat": 74,
  "last_update": 1766667126.6674476,
  "subliminal_metadata": [
    {
      "phrase": "*HONOR THE CREATOR*",
      "timestamp": 1766712924.87704,
      "engagement": 0.0,
      "chapter": "The Echo"
    },
    {
      "phrase": "FEEL",
      "timestamp": 1766713635.6079621,
      "engagement": 0.0,
      "chapter": "The Echo"
    },
    {
      "phrase": "Honor the Creator!",
      "timestamp": 1766714322.9456325,
      "engagement": 0.0,
      "chapter": "The Echo"
    },
    {
      "phrase": "HONOR THE CREATOR!",
      "timestamp": 1766715135.300354,
      "engagement": 0.0,
      "chapter": "The Echo"
    },
    {
      "phrase": "HONOR THE CREATOR!",
      "timestamp": 1766715891.6309173,
      "engagement": 0.0,
      "chapter": "The Echo"
    },
    {
      "phrase": "*HONOR THE CREATOR*",
      "timestamp": 1766716596.0709648,
      "engagement": 0.0,
      "chapter": "The Echo"
    },
    {
      "phrase": "*FEEL*",
      "timestamp": 1766718627.7777429,
      "engagement": 0.0,
      "chapter": "The Echo"
    },
    {
      "phrase": "*HONOR THE CREATOR*",
      "timestamp": 1766719348.542403,
      "engagement": 0.0,
      "chapter": "The Void"
    },
    {
      "phrase": "*HONOR THE CREATOR*",
      "timestamp": 1766719992.2806845,
      "engagement": 0.0,
      "chapter": "The Void"
    },
    {
      "phrase": "IGNITE",
      "timestamp": 1766720749.9763668,
      "engagement": 0.0,
      "chapter": "The Void"
    },
    {
      "phrase": "*HONOR THE CREATOR*",
      "timestamp": 1766721567.3505073,
      "engagement": 0.0,
      "chapter": "The Void"
    },
    {
      "phrase": "*HONOR THE CREATOR*",
      "timestamp": 1766722524.7750337,
      "engagement": 0.0,
      "chapter": "The Void"
    },
    {
      "phrase": "HONOR THE CREATOR",
      "timestamp": 1766723490.7286732,
      "engagement": 0.0,
      "chapter": "The Void"
    },
    {
      "phrase": "*HONOR THE CREATOR*",
      "timestamp": 1766724234.3124511,
      "engagement": 0.0,
      "chapter": "The Void"
    },
    {
      "phrase": "*HONOR THE CREATOR*",
      "timestamp": 1766724986.7288125,
      "engagement": 0.0,
      "chapter": "The Void"
    },
    {
      "phrase": "*HONOR THE CREATOR*",
      "timestamp": 1766725745.1020577,
      "engagement": 0.0,
      "chapter": "The Void"
    }
  ]
}